{
    "wild_encounter_background": {
        "key": "wild_encounter_background",
        "type": "image",
        "path": "assets/img/ui/wild-encounter/{resolution}/background.png",
        "layout": "wildEncounter"
    },
    "wild_encounter_name_box": {
        "key": "wild_encounter_name_box",
        "type": "image",
        "path": "assets/img/ui/wild-encounter/{resolution}/name_box.png",
        "layout": "wildEncounter"
    },
    "wild_button": {
        "key": "wild_button",
        "type": "spritesheet",
        "path": "assets/img/ui/wild-encounter/{resolution}/buttonsheet.png",
        "dimensions": {
            "hd": {
                "frameWidth": 149,
                "frameHeight": 82
            }
        },
        "layout": "wildEncounter"
    },
    "wild_star_rating": {
        "key": "wild_star_rating",
        "type": "spritesheet",
        "path": "assets/img/ui/wild-encounter/{resolution}/rating_star.png",
        "dimensions": {
            "hd": {
                "frameWidth": 53,
                "frameHeight": 51
            }
        },
        "layout": "wildEncounter"
    },
    "party_background": {
        "key": "party_background",
        "type": "image",
        "path": "assets/img/ui/party/{resolution}/background.png",
        "layout": "party"
    },
    "profile_background": {
        "key": "profile_background",
        "type": "image",
        "path": "assets/img/ui/profile/{resolution}/background.png",
        "componentType": "STATIC",
        "layout": "profile"
    },
    "profile_infos": {
        "key": "profile_infos",
        "type": "image",
        "path": "assets/img/ui/profile/{resolution}/infos.png",
        "componentType": "STATIC",
        "layout": "profile"
    },
    "profile_achievements": {
        "key": "profile_achievements",
        "type": "image",
        "path": "assets/img/ui/profile/{resolution}/achievements.png",
        "componentType": "STATIC",
        "layout": "profile"
    },
    "profile_monsters_button": {
        "key": "profile_monsters_button",
        "type": "spritesheet",
        "path": "assets/img/ui/profile/{resolution}/buttonsheet_monster.png",
        "componentType": "BUTTON",
        "dimensions": {
            "hd": {
                "frameWidth": 109,
                "frameHeight": 102
            }
        },
        "layout": "profile"
    },
    "profile_actions_button": {
        "key": "profile_actions_button",
        "type": "spritesheet",
        "path": "assets/img/ui/profile/{resolution}/buttonsheet.png",
        "componentType": "BUTTON",
        "dimensions": {
            "hd": {
                "frameWidth": 176,
                "frameHeight": 60
            }
        }
    },
    "initial_background": {
        "key": "initial_background",
        "type": "image",
        "path": "assets/img/ui/initial/{resolution}/background.png",
        "componentType": "STATIC",
        "layout": "initial"
    },
    "initial_monster_select_button": {
        "key": "initial_monster_select_button",
        "type": "spritesheet",
        "path": "assets/img/ui/initial/{resolution}/monsters_select_spritesheet.png",
        "componentType": "BUTTON",
        "dimensions": {
            "hd": {
                "frameWidth": 349.6666666666667,
                "frameHeight": 367
            }
        }
    },
    "initial_window_accept_reject_button": {
        "key": "initial_window_accept_reject_button",
        "type": "spritesheet",
        "path": "assets/img/ui/initial/{resolution}/choose_spritesheet.png",
        "componentType": "BUTTON",
        "dimensions": {
            "hd": {
                "frameWidth": 252,
                "frameHeight": 87
            }
        }
    },
    "initial_window_background": {
        "key": "initial_window_background",
        "type": "image",
        "path": "assets/img/ui/initial/{resolution}/choose_window.png",
        "componentType": "STATIC",
        "layout": "initial"
    },
    "monsterStatus_background": {
        "key": "monsterStatus_background",
        "type": "image",
        "path": "assets/img/ui/status/{resolution}/background.png",
        "componentType": "STATIC",
        "layout": "monsterStatus"
    },
    "monsterStatus_tab_status": {
        "key": "monsterStatus_tab_status",
        "type": "image",
        "path": "assets/img/ui/status/{resolution}/tab0_status.png",
        "componentType": "TAB",
        "layout": "monsterStatus"
    },
    "monsterStatus_tab_stats": {
        "key": "monsterStatus_tab_stats",
        "type": "image",
        "path": "assets/img/ui/status/{resolution}/tab1_stats.png",
        "componentType": "TAB",
        "layout": "monsterStatus"
    },
    "monsterStatus_tab_moves": {
        "key": "monsterStatus_tab_moves",
        "type": "image",
        "path": "assets/img/ui/status/{resolution}/tab2_moves.png",
        "componentType": "TAB",
        "layout": "monsterStatus"
    }
}
